{"id": "2024102N", "year": "2024", "no": 102, "openDate": "2024-09-10+08:00", "closeDate": "2024-09-12T21:15:00+08:00", "drawDate": "2024-09-12+08:00", "status": "Result", "snowballCode": "", "snowballName_en": "", "snowballName_ch": "", "lotteryPool": {"sell": false, "status": "Payout", "totalInvestment": "38457195", "jackpot": "0", "unitBet": 10, "estimatedPrize": "", "derivedFirstPrizeDiv": "8000000", "lotteryPrizes": [{"type": 1, "winningUnit": 0, "dividend": "0"}, {"type": 2, "winningUnit": 0, "dividend": "0"}, {"type": 3, "winningUnit": 435, "dividend": "94890"}, {"type": 4, "winningUnit": 1235, "dividend": "9600"}, {"type": 5, "winningUnit": 25155, "dividend": "640"}, {"type": 6, "winningUnit": 30727, "dividend": "320"}, {"type": 7, "winningUnit": 485246, "dividend": "40"}]}, "drawResult": {"drawnNo": [14, 18, 20, 25, 32, 43], "xDrawnNo": 45}}