{"id": "2007125N", "year": "2007", "no": 125, "openDate": "2007-10-23+08:00", "closeDate": "2007-10-25T20:45:00+08:00", "drawDate": "2007-10-25+08:00", "status": "Result", "snowballCode": "", "snowballName_en": "", "snowballName_ch": "", "lotteryPool": {"sell": false, "status": "Payout", "totalInvestment": "41596889", "jackpot": "9982880", "unitBet": 5, "estimatedPrize": "", "derivedFirstPrizeDiv": "15647685", "lotteryPrizes": [{"type": 1, "winningUnit": 5, "dividend": "16205905"}, {"type": 2, "winningUnit": 5, "dividend": "2074340"}, {"type": 3, "winningUnit": 605, "dividend": "45715"}, {"type": 4, "winningUnit": 1535, "dividend": "4800"}, {"type": 5, "winningUnit": 31267, "dividend": "320"}, {"type": 6, "winningUnit": 45342, "dividend": "160"}, {"type": 7, "winningUnit": 585011, "dividend": "20"}]}, "drawResult": {"drawnNo": [4, 14, 31, 35, 42, 49], "xDrawnNo": 1}}