{"id": "2007130N", "year": "2007", "no": 130, "openDate": "2007-11-04+08:00", "closeDate": "2007-11-08T20:45:00+08:00", "drawDate": "2007-11-08+08:00", "status": "Result", "snowballCode": "", "snowballName_en": "", "snowballName_ch": "", "lotteryPool": {"sell": false, "status": "Payout", "totalInvestment": "81893626", "jackpot": "22314466", "unitBet": 5, "estimatedPrize": "", "derivedFirstPrizeDiv": "35000000", "lotteryPrizes": [{"type": 1, "winningUnit": 5, "dividend": "32493650"}, {"type": 2, "winningUnit": 55, "dividend": "308460"}, {"type": 3, "winningUnit": 1454, "dividend": "31110"}, {"type": 4, "winningUnit": 4152, "dividend": "4800"}, {"type": 5, "winningUnit": 91470, "dividend": "320"}, {"type": 6, "winningUnit": 102846, "dividend": "160"}, {"type": 7, "winningUnit": 1558471, "dividend": "20"}]}, "drawResult": {"drawnNo": [6, 14, 18, 28, 30, 37], "xDrawnNo": 21}}