{"id": "2001032N", "year": "2001", "no": 32, "openDate": "", "closeDate": "2001-04-24T18:45:00+08:00", "drawDate": "2001-04-24+08:00", "status": "Result", "snowballCode": "", "snowballName_en": "", "snowballName_ch": "", "lotteryPool": {"sell": false, "status": "Payout", "totalInvestment": "45382086", "jackpot": "10250045", "unitBet": 5, "estimatedPrize": "", "derivedFirstPrizeDiv": "", "lotteryPrizes": [{"type": 1, "winningUnit": 0, "dividend": "0"}, {"type": 2, "winningUnit": 15, "dividend": "906715"}, {"type": 3, "winningUnit": 700, "dividend": "55860"}, {"type": 4, "winningUnit": 2110, "dividend": "4500"}, {"type": 5, "winningUnit": 43449, "dividend": "300"}, {"type": 6, "winningUnit": 57327, "dividend": "150"}]}, "drawResult": {"drawnNo": [14, 18, 26, 27, 33, 41], "xDrawnNo": 35}}