{"id": "2001059N", "year": "2001", "no": 59, "openDate": "", "closeDate": "2001-07-19T20:00:00+08:00", "drawDate": "2001-07-19+08:00", "status": "Result", "snowballCode": "", "snowballName_en": "", "snowballName_ch": "", "lotteryPool": {"sell": false, "status": "Payout", "totalInvestment": "42794531", "jackpot": "14033203", "unitBet": 5, "estimatedPrize": "", "derivedFirstPrizeDiv": "", "lotteryPrizes": [{"type": 1, "winningUnit": 10, "dividend": "9768665"}, {"type": 2, "winningUnit": 10, "dividend": "1158760"}, {"type": 3, "winningUnit": 765, "dividend": "43545"}, {"type": 4, "winningUnit": 2602, "dividend": "4500"}, {"type": 5, "winningUnit": 48461, "dividend": "300"}, {"type": 6, "winningUnit": 76160, "dividend": "150"}]}, "drawResult": {"drawnNo": [1, 5, 9, 23, 30, 41], "xDrawnNo": 4}}