{"id": "2014107N", "year": "2014", "no": 107, "openDate": "2014-09-16+08:00", "closeDate": "2014-09-18T21:15:00+08:00", "drawDate": "2014-09-18+08:00", "status": "Result", "snowballCode": "", "snowballName_en": "", "snowballName_ch": "", "lotteryPool": {"sell": false, "status": "Payout", "totalInvestment": "41943261", "jackpot": "9738149", "unitBet": 10, "estimatedPrize": "", "derivedFirstPrizeDiv": "15450124", "lotteryPrizes": [{"type": 1, "winningUnit": 0, "dividend": "0"}, {"type": 2, "winningUnit": 0, "dividend": "0"}, {"type": 3, "winningUnit": 570, "dividend": "94530"}, {"type": 4, "winningUnit": 1350, "dividend": "9600"}, {"type": 5, "winningUnit": 35333, "dividend": "640"}, {"type": 6, "winningUnit": 46552, "dividend": "320"}, {"type": 7, "winningUnit": 699741, "dividend": "40"}]}, "drawResult": {"drawnNo": [6, 16, 20, 25, 27, 45], "xDrawnNo": 29}}