{"id": "2023024N", "year": "2023", "no": 24, "openDate": "2023-03-02+08:00", "closeDate": "2023-03-04T21:15:00+08:00", "drawDate": "2023-03-04+08:00", "status": "Result", "snowballCode": "", "snowballName_en": "", "snowballName_ch": "", "lotteryPool": {"sell": false, "status": "Payout", "totalInvestment": "41536994", "jackpot": "9897100", "unitBet": 10, "estimatedPrize": "", "derivedFirstPrizeDiv": "15553749", "lotteryPrizes": [{"type": 1, "winningUnit": 0, "dividend": "0"}, {"type": 2, "winningUnit": 20, "dividend": "1015520"}, {"type": 3, "winningUnit": 445, "dividend": "121710"}, {"type": 4, "winningUnit": 1730, "dividend": "9600"}, {"type": 5, "winningUnit": 29681, "dividend": "640"}, {"type": 6, "winningUnit": 47254, "dividend": "320"}, {"type": 7, "winningUnit": 619497, "dividend": "40"}]}, "drawResult": {"drawnNo": [1, 9, 15, 26, 42, 44], "xDrawnNo": 25}}