{"id": "2023090N", "year": "2023", "no": 90, "openDate": "2023-08-10+08:00", "closeDate": "2023-08-12T21:15:00+08:00", "drawDate": "2023-08-12+08:00", "status": "Result", "snowballCode": "", "snowballName_en": "", "snowballName_ch": "", "lotteryPool": {"sell": false, "status": "Payout", "totalInvestment": "44887425", "jackpot": "12390062", "unitBet": 10, "estimatedPrize": "", "derivedFirstPrizeDiv": "18502984", "lotteryPrizes": [{"type": 1, "winningUnit": 0, "dividend": "0"}, {"type": 2, "winningUnit": 20, "dividend": "952280"}, {"type": 3, "winningUnit": 720, "dividend": "70530"}, {"type": 4, "winningUnit": 2174, "dividend": "9600"}, {"type": 5, "winningUnit": 47366, "dividend": "640"}, {"type": 6, "winningUnit": 56509, "dividend": "320"}, {"type": 7, "winningUnit": 839876, "dividend": "40"}]}, "drawResult": {"drawnNo": [3, 12, 13, 17, 24, 36], "xDrawnNo": 16}}