{"id": "2011089N", "year": "2011", "no": 89, "openDate": "2011-07-26+08:00", "closeDate": "2011-07-28T21:15:00+08:00", "drawDate": "2011-07-28+08:00", "status": "Result", "snowballCode": "", "snowballName_en": "", "snowballName_ch": "", "lotteryPool": {"sell": false, "status": "Payout", "totalInvestment": "73849714", "jackpot": "40761557", "unitBet": 10, "estimatedPrize": "", "derivedFirstPrizeDiv": "50818662", "lotteryPrizes": [{"type": 1, "winningUnit": 15, "dividend": "34706930"}, {"type": 2, "winningUnit": 0, "dividend": "0"}, {"type": 3, "winningUnit": 1100, "dividend": "91300"}, {"type": 4, "winningUnit": 2110, "dividend": "9600"}, {"type": 5, "winningUnit": 59457, "dividend": "640"}, {"type": 6, "winningUnit": 61367, "dividend": "320"}, {"type": 7, "winningUnit": 1123112, "dividend": "40"}]}, "drawResult": {"drawnNo": [11, 21, 30, 36, 42, 47], "xDrawnNo": 34}}