{"id": "2015120N", "year": "2015", "no": 120, "openDate": "2015-10-15+08:00", "closeDate": "2015-10-17T21:15:00+08:00", "drawDate": "2015-10-17+08:00", "status": "Result", "snowballCode": "", "snowballName_en": "", "snowballName_ch": "", "lotteryPool": {"sell": false, "status": "Payout", "totalInvestment": "38046569", "jackpot": "9672350", "unitBet": 10, "estimatedPrize": "", "derivedFirstPrizeDiv": "15000000", "lotteryPrizes": [{"type": 1, "winningUnit": 0, "dividend": "0"}, {"type": 2, "winningUnit": 10, "dividend": "1851340"}, {"type": 3, "winningUnit": 475, "dividend": "103930"}, {"type": 4, "winningUnit": 1645, "dividend": "9600"}, {"type": 5, "winningUnit": 28037, "dividend": "640"}, {"type": 6, "winningUnit": 43795, "dividend": "320"}, {"type": 7, "winningUnit": 551788, "dividend": "40"}]}, "drawResult": {"drawnNo": [2, 12, 19, 33, 34, 48], "xDrawnNo": 24}}