{"id": "2010119N", "year": "2010", "no": 119, "openDate": "2010-10-09+08:00", "closeDate": "2010-10-12T20:45:00+08:00", "drawDate": "2010-10-12+08:00", "status": "Result", "snowballCode": "", "snowballName_en": "", "snowballName_ch": "", "lotteryPool": {"sell": false, "status": "Payout", "totalInvestment": "27792821", "jackpot": "1419307", "unitBet": 5, "estimatedPrize": "", "derivedFirstPrizeDiv": "5204227", "lotteryPrizes": [{"type": 1, "winningUnit": 5, "dividend": "5236415"}, {"type": 2, "winningUnit": 20, "dividend": "318090"}, {"type": 3, "winningUnit": 460, "dividend": "36880"}, {"type": 4, "winningUnit": 1340, "dividend": "4800"}, {"type": 5, "winningUnit": 23835, "dividend": "320"}, {"type": 6, "winningUnit": 34030, "dividend": "160"}, {"type": 7, "winningUnit": 446482, "dividend": "20"}]}, "drawResult": {"drawnNo": [9, 13, 21, 24, 38, 46], "xDrawnNo": 27}}