{"id": "2019135N", "year": "2019", "no": 135, "openDate": "2019-12-05+08:00", "closeDate": "2019-12-07T21:15:00+08:00", "drawDate": "2019-12-07+08:00", "status": "Result", "snowballCode": "", "snowballName_en": "", "snowballName_ch": "", "lotteryPool": {"sell": false, "status": "Payout", "totalInvestment": "44848278", "jackpot": "11704661", "unitBet": 10, "estimatedPrize": "", "derivedFirstPrizeDiv": "17812252", "lotteryPrizes": [{"type": 1, "winningUnit": 0, "dividend": "0"}, {"type": 2, "winningUnit": 0, "dividend": "0"}, {"type": 3, "winningUnit": 580, "dividend": "103250"}, {"type": 4, "winningUnit": 1737, "dividend": "9600"}, {"type": 5, "winningUnit": 32880, "dividend": "640"}, {"type": 6, "winningUnit": 47016, "dividend": "320"}, {"type": 7, "winningUnit": 622089, "dividend": "40"}]}, "drawResult": {"drawnNo": [14, 25, 26, 30, 32, 47], "xDrawnNo": 4}}