{"id": "1997010N", "year": "1997", "no": 10, "openDate": "", "closeDate": "", "drawDate": "1997-02-04+08:00", "status": "Result", "snowballCode": "", "snowballName_en": "Chinese New Year Snowball", "snowballName_ch": "\u65b0\u6625\u91d1\u591a\u5bf6", "lotteryPool": {"sell": false, "status": "Payout", "totalInvestment": "", "jackpot": "", "unitBet": 5, "estimatedPrize": "", "derivedFirstPrizeDiv": "", "lotteryPrizes": [{"type": 1, "winningUnit": 15, "dividend": "17300080"}]}, "drawResult": {"drawnNo": [29, 34, 37, 39, 40, 43], "xDrawnNo": 32}}