{"id": "2005118N", "year": "2005", "no": 118, "openDate": "2005-10-04+08:00", "closeDate": "2005-10-06T20:00:00+08:00", "drawDate": "2005-10-06+08:00", "status": "Result", "snowballCode": "", "snowballName_en": "", "snowballName_ch": "", "lotteryPool": {"sell": false, "status": "Payout", "totalInvestment": "35500668", "jackpot": "5000000", "unitBet": 5, "estimatedPrize": "", "derivedFirstPrizeDiv": "10000000", "lotteryPrizes": [{"type": 1, "winningUnit": 0, "dividend": "0"}, {"type": 2, "winningUnit": 10, "dividend": "864140"}, {"type": 3, "winningUnit": 565, "dividend": "40785"}, {"type": 4, "winningUnit": 1435, "dividend": "4800"}, {"type": 5, "winningUnit": 30381, "dividend": "320"}, {"type": 6, "winningUnit": 42201, "dividend": "160"}, {"type": 7, "winningUnit": 527209, "dividend": "20"}]}, "drawResult": {"drawnNo": [23, 26, 27, 29, 30, 45], "xDrawnNo": 18}}