{"id": "2005116N", "year": "2005", "no": 116, "openDate": "2005-09-27+08:00", "closeDate": "2005-09-30T21:00:00+08:00", "drawDate": "2005-09-30+08:00", "status": "Result", "snowballCode": "", "snowballName_en": "", "snowballName_ch": "", "lotteryPool": {"sell": false, "status": "Payout", "totalInvestment": "104454578", "jackpot": "31002624", "unitBet": 5, "estimatedPrize": "", "derivedFirstPrizeDiv": "45540240", "lotteryPrizes": [{"type": 1, "winningUnit": 5, "dividend": "45986230"}, {"type": 2, "winningUnit": 65, "dividend": "384195"}, {"type": 3, "winningUnit": 1620, "dividend": "41105"}, {"type": 4, "winningUnit": 4650, "dividend": "4800"}, {"type": 5, "winningUnit": 87996, "dividend": "320"}, {"type": 6, "winningUnit": 128225, "dividend": "160"}, {"type": 7, "winningUnit": 1600850, "dividend": "20"}]}, "drawResult": {"drawnNo": [11, 14, 20, 24, 25, 35], "xDrawnNo": 33}}