{"id": "2005001N", "year": "2005", "no": 1, "openDate": "2004-12-30+08:00", "closeDate": "2005-01-02T20:00:00+08:00", "drawDate": "2005-01-02+08:00", "status": "Result", "snowballCode": "", "snowballName_en": "", "snowballName_ch": "", "lotteryPool": {"sell": false, "status": "Payout", "totalInvestment": "32954421", "jackpot": "5000000", "unitBet": 5, "estimatedPrize": "", "derivedFirstPrizeDiv": "10000000", "lotteryPrizes": [{"type": 1, "winningUnit": 5, "dividend": "9823555"}, {"type": 2, "winningUnit": 5, "dividend": "1607850"}, {"type": 3, "winningUnit": 900, "dividend": "23820"}, {"type": 4, "winningUnit": 970, "dividend": "4800"}, {"type": 5, "winningUnit": 32254, "dividend": "320"}, {"type": 6, "winningUnit": 35066, "dividend": "160"}, {"type": 7, "winningUnit": 537998, "dividend": "20"}]}, "drawResult": {"drawnNo": [11, 18, 32, 36, 39, 43], "xDrawnNo": 34}}